pytroll_runner/__init__.py
pytroll_runner/tests/__init__.py
pytroll_runner/tests/test_runner.py
pytroll_runner-0.2.0.dist-info/licenses/LICENSE
pytroll_runner-0.2.0.dist-info/METADATA
pytroll_runner-0.2.0.dist-info/WHEEL
pytroll_runner-0.2.0.dist-info/entry_points.txt
pytroll_runner-0.2.0.dist-info/top_level.txt
pytroll_runner-0.2.0.dist-info/RECORD
